README.rst
setup.cfg
setup.py
CsCntlr/CsCntlr.py
CsCntlr/__init__.py
CsCntlr.egg-info/PKG-INFO
CsCntlr.egg-info/SOURCES.txt
CsCntlr.egg-info/dependency_links.txt
CsCntlr.egg-info/requires.txt
CsCntlr.egg-info/top_level.txt
CsCntlr/__modes/CsABC.py
CsCntlr/__modes/CsFPM.py
CsCntlr/__modes/CsMSM.py
CsCntlr/__modes/__init__.py