Metadata-Version: 1.1
Name: CsCntlr
Version: 0.0.8
Summary: A python package for the color sensor S11059-02DT
Home-page: https://github.com/NariseT/CsCntlr
Author: Takafumi Narise
Author-email: narise.pub@gmail.com
License: MIT
Keywords: Color-sensor S11059-02DT Raspberry-Pi
Platform: UNKNOWN
Classifier: Development Status :: 3 - Alpha
Classifier: Environment :: Console
Classifier: Operating System :: Other OS
Classifier: Intended Audience :: Developers
Classifier: Intended Audience :: Education
Classifier: Intended Audience :: Science/Research
Classifier: Topic :: Scientific/Engineering :: Bio-Informatics
Classifier: Topic :: Scientific/Engineering :: Information Analysis
Classifier: License :: OSI Approved :: MIT License
Classifier: Programming Language :: Python :: 2.7
